Kimton/__init__.py
Kimton/__main__.py
Kimton/craft.py
kimton-0.0.1.dist-info/LICENSE
kimton-0.0.1.dist-info/METADATA
kimton-0.0.1.dist-info/WHEEL
kimton-0.0.1.dist-info/top_level.txt
kimton-0.0.1.dist-info/RECORD
